wwpdb/apps/chemeditor/__init__.py
wwpdb/apps/chemeditor/webapp/AtomMatch.py
wwpdb/apps/chemeditor/webapp/CVSCommit.py
wwpdb/apps/chemeditor/webapp/ChemCompDbUtil.py
wwpdb/apps/chemeditor/webapp/ChemCompHash.py
wwpdb/apps/chemeditor/webapp/ChemEditorBase.py
wwpdb/apps/chemeditor/webapp/ChemEditorWebApp.py
wwpdb/apps/chemeditor/webapp/DaInternalCombineDb.py
wwpdb/apps/chemeditor/webapp/Enumeration.py
wwpdb/apps/chemeditor/webapp/Get2D.py
wwpdb/apps/chemeditor/webapp/GetLigand.py
wwpdb/apps/chemeditor/webapp/SaveLigand.py
wwpdb/apps/chemeditor/webapp/Search.py
wwpdb/apps/chemeditor/webapp/UpdateLigand.py
wwpdb/apps/chemeditor/webapp/Upload.py
wwpdb/apps/chemeditor/webapp/Utils.py
wwpdb/apps/chemeditor/webapp/__init__.py
wwpdb/apps/chemeditor/webapp/doServiceRequestWebOb.fcgi
wwpdb/apps/chemeditor/webapp/doServiceRequestWebOb.wsgi
wwpdb_apps_chemeditor-0.17.1.dist-info/METADATA
wwpdb_apps_chemeditor-0.17.1.dist-info/WHEEL
wwpdb_apps_chemeditor-0.17.1.dist-info/RECORD
