Metadata-Version: 2.4
Name: wwpdb.apps.chemeditor
Version: 0.17.1
Summary: wwPDB chemical editor
Project-URL: Homepage, https://github.com/rcsb/py-wwpdb_apps_chemeditor
Author-email: Ezra Peisach <ezra.peisach@rcsb.org>
License-Expression: Apache-2.0
Classifier: Development Status :: 3 - Alpha
Classifier: Intended Audience :: Developers
Classifier: License :: OSI Approved :: Apache Software License
Classifier: Natural Language :: English
Classifier: Programming Language :: Python
Classifier: Programming Language :: Python :: 2.7
Classifier: Programming Language :: Python :: 3
Classifier: Programming Language :: Python :: 3.6
Classifier: Programming Language :: Python :: 3.7
Requires-Python: >=3.6
Requires-Dist: wwpdb-apps-ccmodule>=0.4
Requires-Dist: wwpdb-io>=0.34
Requires-Dist: wwpdb-utils-config~=0.34
Requires-Dist: wwpdb-utils-db
Requires-Dist: wwpdb-utils-session
